ufyCV/__init__.py
ufyCV/core/__init__.py
ufyCV/core/yolo.py
ufyCV/core/yolo_postprocess.py
ufyCV/risk/__init__.py
ufyCV/risk/risk_recognition.py
ufyCV/utils/__init__.py
ufyCV/utils/img2base64.py
ufyCV/utils/results2alarm.py
ufycv-0.0.6.dist-info/METADATA
ufycv-0.0.6.dist-info/WHEEL
ufycv-0.0.6.dist-info/top_level.txt
ufycv-0.0.6.dist-info/RECORD
