Metadata-Version: 2.4
Name: ufyCV
Version: 0.0.6
Summary: a python package for computer vision
Home-page: https://github.com/ufy2024/ufyCV.git
Author: ufy
Author-email: antarm@outlook.com
Requires-Dist: numpy
Requires-Dist: torch
Requires-Dist: ultralytics==8.2.31
Requires-Dist: tritonclient[all]
Requires-Dist: opencv-python
Dynamic: author
Dynamic: author-email
Dynamic: home-page
Dynamic: requires-dist
Dynamic: summary
